aTeam_PySparkLibrary/__init__.py
aTeam_PySparkLibrary/add_unidentified_row.py
aTeam_PySparkLibrary/generate_dim_date_table.py
aTeam_PySparkLibrary/get_lakehouse_path.py
aTeam_PySparkLibrary/perform_delta_load.py
aTeam_PySparkLibrary/propagate_value_over_period.py
aTeam_PySparkLibrary/helpFunctions/exists_and_has_files.py
aTeam_PySparkLibrary/helpFunctions/calendar_table/LICENSE
aTeam_PySparkLibrary/helpFunctions/calendar_table/README.md
aTeam_PySparkLibrary/helpFunctions/calendar_table/calendar_table.py
aTeam_PySparkLibrary/helpFunctions/calendar_table/docs/__init__.py
aTeam_PySparkLibrary/helpFunctions/calendar_table/docs/col_descriptions.csv
aTeam_PySparkLibrary/helpFunctions/calendar_table/docs/input/desc.csv
aTeam_PySparkLibrary/helpFunctions/calendar_table/udfs/__init__.py
aTeam_PySparkLibrary/helpFunctions/calendar_table/udfs/date_udfs.py
aTeam_PySparkLibrary/helpFunctions/calendar_table/udfs/df_udfs.py
ateam_pysparklibrary-0.0.49.dist-info/METADATA
ateam_pysparklibrary-0.0.49.dist-info/WHEEL
ateam_pysparklibrary-0.0.49.dist-info/licenses/LICENSE
ateam_pysparklibrary-0.0.49.dist-info/RECORD
