Metadata-Version: 2.4
Name: aTeam-PySparkLibrary
Version: 0.0.49
Project-URL: Homepage, https://github.com/EgdeConsulting/aTeam-PySparkLibrary
Project-URL: Issues, https://github.com/EgdeConsulting/aTeam-PySparkLibrary/issues
Author-email: Egde A-team <ludvig.loite@egde.no>
License-File: LICENSE
Classifier: License :: OSI Approved :: MIT License
Classifier: Operating System :: OS Independent
Classifier: Programming Language :: Python :: 3
Requires-Python: >=3.8
